{
  "id": "version-3.8.2/用户使用手册/网页端/权限设置",
  "title": "权限设置",
  "description": "权限设置主要用来管理和配置库存各功能的管理员，和知识库是否需要审核、管理员是谁。\r",
  "source": "@site/versioned_docs\\version-3.8.2\\用户使用手册\\网页端\\权限设置.md",
  "permalink": "/docs/3.8.2/用户使用手册/网页端/权限设置",
  "editUrl": "https://www.rockwellautomation.com.cn/support.html/edit/master/versioned_docs\\version-3.8.2\\用户使用手册\\网页端\\权限设置.md",
  "version": "3.8.2",
  "lastUpdatedAt": 1613647399,
  "sidebar": "version-3.8.2/someSidebar",
  "previous": {
    "title": "消息类型管理",
    "permalink": "/docs/3.8.2/用户使用手册/网页端/消息类型管理"
  },
  "next": {
    "title": "网站设置",
    "permalink": "/docs/3.8.2/用户使用手册/网页端/网站设置"
  }
}